odoo9_addon_connector_prestashop-9.0.1.0.6-py2.7-nspkg.pth
odoo9_addon_connector_prestashop-9.0.1.0.6.dist-info/DESCRIPTION.rst
odoo9_addon_connector_prestashop-9.0.1.0.6.dist-info/METADATA
odoo9_addon_connector_prestashop-9.0.1.0.6.dist-info/RECORD
odoo9_addon_connector_prestashop-9.0.1.0.6.dist-info/WHEEL
odoo9_addon_connector_prestashop-9.0.1.0.6.dist-info/metadata.json
odoo9_addon_connector_prestashop-9.0.1.0.6.dist-info/namespace_packages.txt
odoo9_addon_connector_prestashop-9.0.1.0.6.dist-info/top_level.txt
odoo_addons/connector_prestashop/README.rst
odoo_addons/connector_prestashop/__init__.py
odoo_addons/connector_prestashop/__openerp__.py
odoo_addons/connector_prestashop/backend.py
odoo_addons/connector_prestashop/connector.py
odoo_addons/connector_prestashop/consumer.py
odoo_addons/connector_prestashop/data/cron.xml
odoo_addons/connector_prestashop/data/ecommerce_data.xml
odoo_addons/connector_prestashop/data/product_decimal_precision.xml
odoo_addons/connector_prestashop/demo/backend.xml
odoo_addons/connector_prestashop/models/__init__.py
odoo_addons/connector_prestashop/models/account_invoice/__init__.py
odoo_addons/connector_prestashop/models/account_invoice/common.py
odoo_addons/connector_prestashop/models/account_invoice/importer.py
odoo_addons/connector_prestashop/models/account_payment_mode/__init__.py
odoo_addons/connector_prestashop/models/account_payment_mode/common.py
odoo_addons/connector_prestashop/models/account_payment_mode/importer.py
odoo_addons/connector_prestashop/models/account_tax/__init__.py
odoo_addons/connector_prestashop/models/account_tax/common.py
odoo_addons/connector_prestashop/models/account_tax/importer.py
odoo_addons/connector_prestashop/models/account_tax_group/__init__.py
odoo_addons/connector_prestashop/models/account_tax_group/common.py
odoo_addons/connector_prestashop/models/account_tax_group/importer.py
odoo_addons/connector_prestashop/models/binding/__init__.py
odoo_addons/connector_prestashop/models/binding/common.py
odoo_addons/connector_prestashop/models/delivery_carrier/__init__.py
odoo_addons/connector_prestashop/models/delivery_carrier/common.py
odoo_addons/connector_prestashop/models/delivery_carrier/exporter.py
odoo_addons/connector_prestashop/models/delivery_carrier/importer.py
odoo_addons/connector_prestashop/models/mail_message/__init__.py
odoo_addons/connector_prestashop/models/mail_message/common.py
