Metadata-Version: 2.0
Name: odoo9-addon-connector-prestashop
Version: 9.0.1.0.6
Summary: PrestaShop-Odoo connector
Home-page: https://github.com/OCA/connector-prestashop
Author: Akretion,Camptocamp,AvanzOSC,Tecnativa,Odoo Community Association (OCA)
Author-email: support@odoo-community.org
License: AGPL-3
Platform: UNKNOWN
Classifier: Programming Language :: Python :: 2.7
Classifier: Framework :: Odoo
Classifier: License :: OSI Approved :: GNU Affero General Public License v3
Requires-Dist: bs4
Requires-Dist: freezegun
Requires-Dist: html2text
Requires-Dist: odoo (<9.1a,>=9.0a)
Requires-Dist: odoo9-addon-connector-ecommerce
Requires-Dist: odoo9-addon-product-multi-category
Requires-Dist: odoo9-addon-product-multi-image
Requires-Dist: odoo9-addon-product-variant-supplierinfo
Requires-Dist: prestapyt
Requires-Dist: vcr
